[
    {
        "id": 1,
        "title": "Epic Gaming Montage",
        "description": "Valorant highlights",
        "category": "gameplay",
        "icon": "fa-gamepad",
        "thumbnail": "",
        "videoUrl": "https://www.youtube.com/embed/dQw4w9WgXcQ"
    },
    {
        "id": 2,
        "title": "Music Visualizer",
        "description": "Cinematic music video",
        "category": "video",
        "icon": "fa-film",
        "thumbnail": "",
        "videoUrl": "https://www.youtube.com/embed/jNQXAC9IVRw"
    },
    {
        "id": 3,
        "title": "Short Film Edit",
        "description": "Narrative storytelling",
        "category": "video",
        "icon": "fa-film",
        "thumbnail": "",
        "videoUrl": "https://www.youtube.com/embed/8c5G3orRzs8"
    },
    {
        "id": 4,
        "title": "Color Grade Showcase",
        "description": "Before/after comparison",
        "category": "color-grading",
        "icon": "fa-palette",
        "thumbnail": "",
        "videoUrl": "https://www.youtube.com/embed/LXb3EKWsInQ"
    },
    {
        "id": 5,
        "title": "Motion Reel",
        "description": "Custom animations & VFX",
        "category": "motion-graphics",
        "icon": "fa-magic",
        "thumbnail": "",
        "videoUrl": "https://www.youtube.com/embed/ScMzIvxBSi4"
    },
    {
        "id": 6,
        "title": "Vlog Compilation",
        "description": "Engaging vlog content",
        "category": "video",
        "icon": "fa-film",
        "thumbnail": "",
        "videoUrl": "https://www.youtube.com/embed/9bZkp7q19f0"
    }
]
